eqs/__init__.py
eqs/main.py
eqs-0.0.1.dist-info/LICENSE
eqs-0.0.1.dist-info/METADATA
eqs-0.0.1.dist-info/WHEEL
eqs-0.0.1.dist-info/entry_points.txt
eqs-0.0.1.dist-info/top_level.txt
eqs-0.0.1.dist-info/RECORD
